imdb/__init__.py
imdb/imdb.py
tdm_proj09-0.0.1.dist-info/LICENSE
tdm_proj09-0.0.1.dist-info/METADATA
tdm_proj09-0.0.1.dist-info/WHEEL
tdm_proj09-0.0.1.dist-info/top_level.txt
tdm_proj09-0.0.1.dist-info/RECORD
