Metadata-Version: 2.1
Name: tdm-proj09
Version: 0.0.1
Summary: tdm project 09
Author-email: darren <iyerd@purdue.edu>
License: MIT License        
Keywords: example,imdb,tutorial,seminar
Classifier: License :: OSI Approved :: MIT License
Classifier: Programming Language :: Python
Classifier: Programming Language :: Python :: 3
Requires-Python: >=3.10
License-File: LICENSE
Requires-Dist: lxml (>=4.9.1)
Requires-Dist: requests (>=2.28.1)
